<?xml version="1.0" encoding="utf-8"?>
<TextureAtlas imagePath="P2Sonic_Assets.png">
	<!-- Created with Adobe Animate version 21.0.3.38773 -->
	<!-- http://www.adobe.com/products/animate.html -->
	<SubTexture name="NewPhase2Sonic Down instance 10000" x="0" y="0" width="559" height="674"/>
	<SubTexture name="NewPhase2Sonic Down instance 10001" x="559" y="0" width="559" height="674"/>
	<SubTexture name="NewPhase2Sonic Down instance 10002" x="1118" y="0" width="559" height="674"/>
	<SubTexture name="NewPhase2Sonic Down instance 10003" x="1118" y="0" width="559" height="674"/>
	<SubTexture name="NewPhase2Sonic Down instance 10004" x="1118" y="0" width="559" height="674"/>
	<SubTexture name="NewPhase2Sonic Down instance 10005" x="1118" y="0" width="559" height="674"/>
	<SubTexture name="NewPhase2Sonic Down instance 10006" x="1118" y="0" width="559" height="674"/>
	<SubTexture name="NewPhase2Sonic Down instance 10007" x="1118" y="0" width="559" height="674"/>
	<SubTexture name="NewPhase2Sonic Down instance 10008" x="1118" y="0" width="559" height="674"/>
	<SubTexture name="NewPhase2Sonic Down instance 10009" x="1118" y="0" width="559" height="674"/>
	<SubTexture name="NewPhase2Sonic Down instance 10010" x="1118" y="0" width="559" height="674"/>
	<SubTexture name="NewPhase2Sonic Idle instance 10000" x="1677" y="0" width="608" height="818"/>
	<SubTexture name="NewPhase2Sonic Idle instance 10001" x="2285" y="0" width="608" height="818"/>
	<SubTexture name="NewPhase2Sonic Idle instance 10002" x="0" y="818" width="608" height="818"/>
	<SubTexture name="NewPhase2Sonic Idle instance 10003" x="608" y="818" width="608" height="818"/>
	<SubTexture name="NewPhase2Sonic Idle instance 10004" x="1216" y="818" width="608" height="818"/>
	<SubTexture name="NewPhase2Sonic Idle instance 10005" x="1824" y="818" width="608" height="818"/>
	<SubTexture name="NewPhase2Sonic Idle instance 10006" x="2432" y="818" width="608" height="818"/>
	<SubTexture name="NewPhase2Sonic Idle instance 10007" x="2432" y="818" width="608" height="818"/>
	<SubTexture name="NewPhase2Sonic Idle instance 10008" x="2432" y="818" width="608" height="818"/>
	<SubTexture name="NewPhase2Sonic Idle instance 10009" x="2432" y="818" width="608" height="818"/>
	<SubTexture name="NewPhase2Sonic Idle instance 10010" x="2432" y="818" width="608" height="818"/>
	<SubTexture name="NewPhase2Sonic Laugh instance 10000" x="0" y="1636" width="752" height="761"/>
	<SubTexture name="NewPhase2Sonic Laugh instance 10001" x="752" y="1636" width="752" height="761"/>
	<SubTexture name="NewPhase2Sonic Laugh instance 10002" x="1504" y="1636" width="752" height="761"/>
	<SubTexture name="NewPhase2Sonic Laugh instance 10003" x="2256" y="1636" width="752" height="761"/>
	<SubTexture name="NewPhase2Sonic Laugh instance 10004" x="2256" y="1636" width="752" height="761"/>
	<SubTexture name="NewPhase2Sonic Laugh instance 10005" x="2256" y="1636" width="752" height="761"/>
	<SubTexture name="NewPhase2Sonic Laugh instance 10006" x="2256" y="1636" width="752" height="761"/>
	<SubTexture name="NewPhase2Sonic Laugh instance 10007" x="2256" y="1636" width="752" height="761"/>
	<SubTexture name="NewPhase2Sonic Laugh instance 10008" x="2256" y="1636" width="752" height="761"/>
	<SubTexture name="NewPhase2Sonic Laugh instance 10009" x="2256" y="1636" width="752" height="761"/>
	<SubTexture name="NewPhase2Sonic Laugh instance 10010" x="2256" y="1636" width="752" height="761"/>
	<SubTexture name="NewPhase2Sonic Left instance 10000" x="0" y="2397" width="838" height="648"/>
	<SubTexture name="NewPhase2Sonic Left instance 10001" x="838" y="2397" width="838" height="648"/>
	<SubTexture name="NewPhase2Sonic Left instance 10002" x="1676" y="2397" width="838" height="648"/>
	<SubTexture name="NewPhase2Sonic Left instance 10003" x="1676" y="2397" width="838" height="648"/>
	<SubTexture name="NewPhase2Sonic Left instance 10004" x="1676" y="2397" width="838" height="648"/>
	<SubTexture name="NewPhase2Sonic Left instance 10005" x="1676" y="2397" width="838" height="648"/>
	<SubTexture name="NewPhase2Sonic Left instance 10006" x="1676" y="2397" width="838" height="648"/>
	<SubTexture name="NewPhase2Sonic Left instance 10007" x="1676" y="2397" width="838" height="648"/>
	<SubTexture name="NewPhase2Sonic Left instance 10008" x="1676" y="2397" width="838" height="648"/>
	<SubTexture name="NewPhase2Sonic Left instance 10009" x="1676" y="2397" width="838" height="648"/>
	<SubTexture name="NewPhase2Sonic Left instance 10010" x="1676" y="2397" width="838" height="648"/>
	<SubTexture name="NewPhase2Sonic Right instance 10000" x="2514" y="2397" width="696" height="615"/>
	<SubTexture name="NewPhase2Sonic Right instance 10001" x="2893" y="0" width="696" height="615"/>
	<SubTexture name="NewPhase2Sonic Right instance 10002" x="3040" y="615" width="696" height="615"/>
	<SubTexture name="NewPhase2Sonic Right instance 10003" x="3040" y="615" width="696" height="615"/>
	<SubTexture name="NewPhase2Sonic Right instance 10004" x="3040" y="615" width="696" height="615"/>
	<SubTexture name="NewPhase2Sonic Right instance 10005" x="3040" y="615" width="696" height="615"/>
	<SubTexture name="NewPhase2Sonic Right instance 10006" x="3040" y="615" width="696" height="615"/>
	<SubTexture name="NewPhase2Sonic Right instance 10007" x="3040" y="615" width="696" height="615"/>
	<SubTexture name="NewPhase2Sonic Right instance 10008" x="3040" y="615" width="696" height="615"/>
	<SubTexture name="NewPhase2Sonic Right instance 10009" x="3040" y="615" width="696" height="615"/>
	<SubTexture name="NewPhase2Sonic Right instance 10010" x="3040" y="615" width="696" height="615"/>
	<SubTexture name="NewPhase2Sonic Up instance 10000" x="3040" y="1230" width="553" height="783"/>
	<SubTexture name="NewPhase2Sonic Up instance 10001" x="3210" y="2013" width="553" height="783"/>
	<SubTexture name="NewPhase2Sonic Up instance 10002" x="3210" y="2796" width="553" height="783"/>
	<SubTexture name="NewPhase2Sonic Up instance 10003" x="3210" y="2796" width="553" height="783"/>
	<SubTexture name="NewPhase2Sonic Up instance 10004" x="3210" y="2796" width="553" height="783"/>
	<SubTexture name="NewPhase2Sonic Up instance 10005" x="3210" y="2796" width="553" height="783"/>
	<SubTexture name="NewPhase2Sonic Up instance 10006" x="3210" y="2796" width="553" height="783"/>
	<SubTexture name="NewPhase2Sonic Up instance 10007" x="3210" y="2796" width="553" height="783"/>
	<SubTexture name="NewPhase2Sonic Up instance 10008" x="3210" y="2796" width="553" height="783"/>
	<SubTexture name="NewPhase2Sonic Up instance 10009" x="3210" y="2796" width="553" height="783"/>
	<SubTexture name="NewPhase2Sonic Up instance 10010" x="3210" y="2796" width="553" height="783"/>
</TextureAtlas>
